divide4bit/divide4bit.v
module compare (
    input [3:0] s1, s2,
    output result_compare
);
assign result_compare = (s1 < s2);
endmodule

module upcounter (
    input clock, reset, enable,
    output reg [3:0] result_counter
);
always @(posedge clock or posedge reset) begin
    if (reset)
        result_counter <= 0;
    else if (enable)
        result_counter <= result_counter + 1;
end
endmodule

module divide4bit (
    input wire clk, rst, start,
    input [3:0] a, b, 
    output reg [3:0] div, remainder,
    output reg done
);
    reg [3:0] temp_dividend;
    reg counting;//trong qua trinh chia
    reg counter_reset;//reset bo dem
    wire lt_signal;//tin hieu so sanh 
    wire [3:0] count;

    upcounter u1 (
        .clock(clk),
        .reset(counter_reset),
        .enable(counting),
        .result_counter(count)
    );

    compare c1 (
        .s1(temp_dividend),
        .s2(b),
        .result_compare(lt_signal)
    );

    always @(posedge clk or posedge rst) begin
        if (rst) begin //rst = 1 => reset tat ca = 0
            div <= 0;
            remainder <= 0;
            temp_dividend <= 0;
            done <= 0;
            counting <= 0;
            counter_reset <= 1;
        end
        else if (start) begin // bat dau
            temp_dividend <= a;
            counting <= 1; //bat tin hieu chia
            done <= 0; 
            counter_reset <= 1; //dam bao bo dem duoc reset
        end
        else if (counting) begin //dang chia
            counter_reset <= 0;
            if (!lt_signal)
                temp_dividend <= temp_dividend - b;
            else begin
                div <= count + 4'b0001;
                remainder <= temp_dividend;
                done <= 1;
                counting <= 0;
            end
        end
    end
endmodule

divide4bit/divide4bit_tb.v
`timescale 1ns/1ps

module divide4bit_tb;
    reg clk, rst, start;
    reg [3:0] a, b;
    wire [3:0] div, remainder;
    wire done;

    divide4bit uut (
        .clk(clk),
        .rst(rst),
        .start(start),
        .a(a),
        .b(b),
        .div(div),
        .remainder(remainder),
        .done(done)
    );

    always #5 clk = ~clk;

    initial begin
        $dumpfile("divide4bit_tb.vcd");
        $dumpvars(0, divide4bit_tb);
        clk = 0; rst = 1; start = 0; a = 0; b = 0;#10;
        rst = 0; #10;

        // Test case 1: 10 / 3
        a = 10; b = 3; start = 1; #10;
        start = 0;
        wait(done);

        // Test case 2: 15 / 4
        #20;
        a = 15; b = 4; start = 1; #10;
        start = 0;
        wait(done);

        // Test case 3: 10 / 5
        #20;
        a = 10; b = 5; start = 1; #10;
        start = 0;
        wait(done);

        #20;
        $finish;
    end
endmodule

divide4bit/divide4bit_tb.vcd
$date
	Fri Mar  7 10:21:46 2025
$end
$version
	Icarus Verilog
$end
$timescale
	1ps
$end
$scope module divide4bit_tb $end
$var wire 4 ! remainder [3:0] $end
$var wire 1 " done $end
$var wire 4 # div [3:0] $end
$var reg 4 $ a [3:0] $end
$var reg 4 % b [3:0] $end
$var reg 1 & clk $end
$var reg 1 ' rst $end
$var reg 1 ( start $end
$scope module uut $end
$var wire 4 ) a [3:0] $end
$var wire 4 * b [3:0] $end
$var wire 1 & clk $end
$var wire 1 ' rst $end
$var wire 1 ( start $end
$var wire 1 + lt_signal $end
$var wire 4 , count [3:0] $end
$var reg 1 - counter_reset $end
$var reg 1 . counting $end
$var reg 4 / div [3:0] $end
$var reg 1 " done $end
$var reg 4 0 remainder [3:0] $end
$var reg 4 1 temp_dividend [3:0] $end
$scope module c1 $end
$var wire 4 2 s1 [3:0] $end
$var wire 4 3 s2 [3:0] $end
$var wire 1 + result_compare $end
$upscope $end
$scope module u1 $end
$var wire 1 & clock $end
$var wire 1 . enable $end
$var wire 1 - reset $end
$var reg 4 4 result_counter [3:0] $end
$upscope $end
$upscope $end
$upscope $end
$enddefinitions $end
$comment Show the parameter values. $end
$dumpall
$end
#0
$dumpvars
b0 4
b0 3
b0 2
b0 1
b0 0
b0 /
0.
1-
b0 ,
0+
b0 *
b0 )
0(
1'
0&
b0 %
b0 $
b0 #
0"
b0 !
$end
#5000
1&
#10000
0&
0'
#15000
1&
#20000
0&
1(
1+
b11 %
b11 *
b11 3
b1010 $
b1010 )
#25000
1.
0+
b1010 1
b1010 2
1&
#30000
0&
0(
#35000
b111 1
b111 2
0-
1&
#40000
0&
#45000
b1 ,
b1 4
b100 1
b100 2
1&
#50000
0&
#55000
b10 ,
b10 4
1+
b1 1
b1 2
1&
#60000
0&
#65000
b11 ,
b11 4
0.
1"
b1 !
b1 0
b11 #
b11 /
1&
#70000
0&
#75000
1&
#80000
0&
#85000
b0 ,
b0 4
1-
0"
1.
0+
b1111 1
b1111 2
1&
1(
b100 %
b100 *
b100 3
b1111 $
b1111 )
#90000
0&
#95000
b1011 1
b1011 2
0-
1&
0(
#100000
0&
#105000
b1 ,
b1 4
b111 1
b111 2
1&
#110000
0&
#115000
b10 ,
b10 4
1+
b11 1
b11 2
1&
#120000
0&
#125000
b11 ,
b11 4
0.
1"
b11 !
b11 0
1&
#130000
0&
#135000
1&
#140000
0&
#145000
b0 ,
b0 4
1-
0"
1.
0+
b1010 1
b1010 2
1&
1(
b101 %
b101 *
b101 3
b1010 $
b1010 )
#150000
0&
#155000
b101 1
b101 2
0-
1&
0(
#160000
0&
#165000
b1 ,
b1 4
1+
b0 1
b0 2
1&
#170000
0&
#175000
b10 ,
b10 4
0.
1"
b0 !
b0 0
b10 #
b10 /
1&
